lineapy/__init__.py
lineapy/__main__.py
lineapy/alembic.ini
lineapy/_alembic/__init__.py
lineapy/_alembic/env.py
lineapy/_alembic/versions/07d0db31e15f_mlflow_integration.py
lineapy/_alembic/versions/38d5f834d3b7_orig.py
lineapy/_alembic/versions/41a413504720_add_named_var.py
lineapy/_alembic/versions/4907800d9126_release_0_1_5.py
lineapy/_alembic/versions/__init__.py
lineapy/annotations/external/boto3.annotations.yaml
lineapy/annotations/external/dask.annotations.yaml
lineapy/annotations/external/gym.annotations.yaml
lineapy/annotations/external/joblib.annotations.yaml
lineapy/annotations/external/keras.annotations.yaml
lineapy/annotations/external/matplotlib.annotations.yaml
lineapy/annotations/external/numpy.annotations.yaml
lineapy/annotations/external/opencv.annotations.yaml
lineapy/annotations/external/pandas.annotations.yaml
lineapy/annotations/external/pillow.annotations.yaml
lineapy/annotations/external/prophet.annotations.yaml
lineapy/annotations/external/sklearn.annotations.yaml
lineapy/annotations/external/statsforecast.annotations.yaml
lineapy/annotations/external/tensorflow.annotations.yaml
lineapy/annotations/external/torch.annotations.yaml
lineapy/annotations/internal/builtins.annotations.yaml
lineapy/annotations/internal/io.annotations.yaml
lineapy/annotations/internal/lineapy.annotations.yaml
lineapy/annotations/internal/operator.annotations.yaml
lineapy/annotations/internal/pickle.annotations.yaml
lineapy/annotations/internal/tempfile.annotations.yaml
lineapy/api/__init__.py
lineapy/api/api.py
lineapy/api/api_utils.py
lineapy/api/artifact_serializer.py
lineapy/api/models/__init__.py
lineapy/api/models/linea_artifact.py
lineapy/api/models/linea_artifact_store.py
lineapy/api/models/pipeline.py
lineapy/cli/__init__.py
lineapy/cli/cli.py
lineapy/data/__init__.py
lineapy/data/graph.py
lineapy/data/types.py
lineapy/db/__init__.py
lineapy/db/db.py
lineapy/db/relational.py
lineapy/db/utils.py
lineapy/editors/__init__.py
lineapy/editors/ipython.py
lineapy-0.2.3.dist-info/LICENSE.txt
lineapy-0.2.3.dist-info/METADATA
lineapy-0.2.3.dist-info/WHEEL
lineapy-0.2.3.dist-info/entry_points.txt
lineapy-0.2.3.dist-info/top_level.txt
lineapy-0.2.3.dist-info/RECORD
