Metadata-Version: 2.1
Name: lineapy
Version: 0.2.3
Summary: Data engineering, simplified. LineaPy creates a frictionless path for taking your data science artifact from development to production.
Home-page: https://github.com/LineaLabs/lineapy/
Author: linealabs
Author-email: dev@lineapy.org
License: Apache License 2.0
Download-URL: https://github.com/LineaLabs/lineapy/
Platform: UNKNOWN
Classifier: Development Status :: 3 - Alpha
Classifier: Programming Language :: Python :: 3
Classifier: Programming Language :: Python :: 3.7
Classifier: Programming Language :: Python :: 3.8
Classifier: Programming Language :: Python :: 3.9
Classifier: Programming Language :: Python :: 3.10
Requires-Python: >=3.7
License-File: LICENSE.txt
Requires-Dist: click (>=8.0.0)
Requires-Dist: pydantic
Requires-Dist: SQLAlchemy (<2.0.0,>=1.4)
Requires-Dist: networkx
Requires-Dist: rich
Requires-Dist: pyyaml
Requires-Dist: asttokens
Requires-Dist: IPython (>=7.0.0)
Requires-Dist: jinja2
Requires-Dist: nbformat
Requires-Dist: nbconvert (<7.0.0)
Requires-Dist: requests
Requires-Dist: fsspec
Requires-Dist: pandas
Requires-Dist: alembic (==1.8.0)
Requires-Dist: cloudpickle
Requires-Dist: typing-extensions (>=4.0.0)
Requires-Dist: black
Requires-Dist: isort
Provides-Extra: dev
Requires-Dist: click (>=8.0.0) ; extra == 'dev'
Requires-Dist: pydantic ; extra == 'dev'
Requires-Dist: SQLAlchemy (<2.0.0,>=1.4) ; extra == 'dev'
Requires-Dist: networkx ; extra == 'dev'
Requires-Dist: rich ; extra == 'dev'
Requires-Dist: pyyaml ; extra == 'dev'
Requires-Dist: asttokens ; extra == 'dev'
Requires-Dist: IPython (>=7.0.0) ; extra == 'dev'
Requires-Dist: jinja2 ; extra == 'dev'
Requires-Dist: nbformat ; extra == 'dev'
Requires-Dist: nbconvert (<7.0.0) ; extra == 'dev'
Requires-Dist: requests ; extra == 'dev'
Requires-Dist: fsspec ; extra == 'dev'
Requires-Dist: pandas ; extra == 'dev'
Requires-Dist: alembic (==1.8.0) ; extra == 'dev'
Requires-Dist: cloudpickle ; extra == 'dev'
Requires-Dist: typing-extensions (>=4.0.0) ; extra == 'dev'
Requires-Dist: black ; extra == 'dev'
Requires-Dist: isort ; extra == 'dev'
Requires-Dist: psycopg2-binary ; extra == 'dev'
Requires-Dist: graphviz ; extra == 'dev'
Requires-Dist: scour (==0.38.2) ; extra == 'dev'
Requires-Dist: astor ; extra == 'dev'
Requires-Dist: altair ; extra == 'dev'
Requires-Dist: scikit-learn ; extra == 'dev'
Requires-Dist: flake8 ; extra == 'dev'
Requires-Dist: fastparquet ; extra == 'dev'
Requires-Dist: matplotlib ; extra == 'dev'
Requires-Dist: jupyterlab ; extra == 'dev'
Requires-Dist: seaborn ; extra == 'dev'
Requires-Dist: Pillow (>=9.0.1) ; extra == 'dev'
Requires-Dist: syrupy (==1.4.5) ; extra == 'dev'
Requires-Dist: pytest ; extra == 'dev'
Requires-Dist: coverage[toml] (<6.0) ; extra == 'dev'
Requires-Dist: pytest-cov ; extra == 'dev'
Requires-Dist: pdbpp ; extra == 'dev'
Requires-Dist: pytest-virtualenv ; extra == 'dev'
Requires-Dist: nbval ; extra == 'dev'
Requires-Dist: coveralls ; extra == 'dev'
Requires-Dist: pre-commit ; extra == 'dev'
Requires-Dist: pytest-xdist ; extra == 'dev'
Requires-Dist: astpretty ; extra == 'dev'
Requires-Dist: scipy ; extra == 'dev'
Requires-Dist: pandoc ; extra == 'dev'
Requires-Dist: mypy ; extra == 'dev'
Requires-Dist: types-PyYAML ; extra == 'dev'
Requires-Dist: types-requests ; extra == 'dev'
Requires-Dist: SQLAlchemy[mypy] (>=1.4.0) ; extra == 'dev'
Requires-Dist: boto3 ; extra == 'dev'
Requires-Dist: s3fs ; extra == 'dev'
Requires-Dist: botocore ; extra == 'dev'
Requires-Dist: mlflow ; extra == 'dev'
Provides-Extra: graph
Requires-Dist: click (>=8.0.0) ; extra == 'graph'
Requires-Dist: pydantic ; extra == 'graph'
Requires-Dist: SQLAlchemy (<2.0.0,>=1.4) ; extra == 'graph'
Requires-Dist: networkx ; extra == 'graph'
Requires-Dist: rich ; extra == 'graph'
Requires-Dist: pyyaml ; extra == 'graph'
Requires-Dist: asttokens ; extra == 'graph'
Requires-Dist: IPython (>=7.0.0) ; extra == 'graph'
Requires-Dist: jinja2 ; extra == 'graph'
Requires-Dist: nbformat ; extra == 'graph'
Requires-Dist: nbconvert (<7.0.0) ; extra == 'graph'
Requires-Dist: requests ; extra == 'graph'
Requires-Dist: fsspec ; extra == 'graph'
Requires-Dist: pandas ; extra == 'graph'
Requires-Dist: alembic (==1.8.0) ; extra == 'graph'
Requires-Dist: cloudpickle ; extra == 'graph'
Requires-Dist: typing-extensions (>=4.0.0) ; extra == 'graph'
Requires-Dist: black ; extra == 'graph'
Requires-Dist: isort ; extra == 'graph'
Requires-Dist: graphviz ; extra == 'graph'
Requires-Dist: scour (==0.38.2) ; extra == 'graph'
Provides-Extra: minimal
Requires-Dist: click (>=8.0.0) ; extra == 'minimal'
Requires-Dist: pydantic ; extra == 'minimal'
Requires-Dist: SQLAlchemy (<2.0.0,>=1.4) ; extra == 'minimal'
Requires-Dist: networkx ; extra == 'minimal'
Requires-Dist: rich ; extra == 'minimal'
Requires-Dist: pyyaml ; extra == 'minimal'
Requires-Dist: asttokens ; extra == 'minimal'
Requires-Dist: IPython (>=7.0.0) ; extra == 'minimal'
Requires-Dist: jinja2 ; extra == 'minimal'
Requires-Dist: nbformat ; extra == 'minimal'
Requires-Dist: nbconvert (<7.0.0) ; extra == 'minimal'
Requires-Dist: requests ; extra == 'minimal'
Requires-Dist: fsspec ; extra == 'minimal'
Requires-Dist: pandas ; extra == 'minimal'
Requires-Dist: alembic (==1.8.0) ; extra == 'minimal'
Requires-Dist: cloudpickle ; extra == 'minimal'
Requires-Dist: typing-extensions (>=4.0.0) ; extra == 'minimal'
Provides-Extra: mlflow
Requires-Dist: click (>=8.0.0) ; extra == 'mlflow'
Requires-Dist: pydantic ; extra == 'mlflow'
Requires-Dist: SQLAlchemy (<2.0.0,>=1.4) ; extra == 'mlflow'
Requires-Dist: networkx ; extra == 'mlflow'
Requires-Dist: rich ; extra == 'mlflow'
Requires-Dist: pyyaml ; extra == 'mlflow'
Requires-Dist: asttokens ; extra == 'mlflow'
Requires-Dist: IPython (>=7.0.0) ; extra == 'mlflow'
Requires-Dist: jinja2 ; extra == 'mlflow'
Requires-Dist: nbformat ; extra == 'mlflow'
Requires-Dist: nbconvert (<7.0.0) ; extra == 'mlflow'
Requires-Dist: requests ; extra == 'mlflow'
Requires-Dist: fsspec ; extra == 'mlflow'
Requires-Dist: pandas ; extra == 'mlflow'
Requires-Dist: alembic (==1.8.0) ; extra == 'mlflow'
Requires-Dist: cloudpickle ; extra == 'mlflow'
Requires-Dist: typing-extensions (>=4.0.0) ; extra == 'mlflow'
Requires-Dist: black ; extra == 'mlflow'
Requires-Dist: isort ; extra == 'mlflow'
Requires-Dist: mlflow ; extra == 'mlflow'
Provides-Extra: postgres
Requires-Dist: click (>=8.0.0) ; extra == 'postgres'
Requires-Dist: pydantic ; extra == 'postgres'
Requires-Dist: SQLAlchemy (<2.0.0,>=1.4) ; extra == 'postgres'
Requires-Dist: networkx ; extra == 'postgres'
Requires-Dist: rich ; extra == 'postgres'
Requires-Dist: pyyaml ; extra == 'postgres'
Requires-Dist: asttokens ; extra == 'postgres'
Requires-Dist: IPython (>=7.0.0) ; extra == 'postgres'
Requires-Dist: jinja2 ; extra == 'postgres'
Requires-Dist: nbformat ; extra == 'postgres'
Requires-Dist: nbconvert (<7.0.0) ; extra == 'postgres'
Requires-Dist: requests ; extra == 'postgres'
Requires-Dist: fsspec ; extra == 'postgres'
Requires-Dist: pandas ; extra == 'postgres'
Requires-Dist: alembic (==1.8.0) ; extra == 'postgres'
Requires-Dist: cloudpickle ; extra == 'postgres'
Requires-Dist: typing-extensions (>=4.0.0) ; extra == 'postgres'
Requires-Dist: black ; extra == 'postgres'
Requires-Dist: isort ; extra == 'postgres'
Requires-Dist: psycopg2-binary ; extra == 'postgres'
Provides-Extra: s3
Requires-Dist: click (>=8.0.0) ; extra == 's3'
Requires-Dist: pydantic ; extra == 's3'
Requires-Dist: SQLAlchemy (<2.0.0,>=1.4) ; extra == 's3'
Requires-Dist: networkx ; extra == 's3'
Requires-Dist: rich ; extra == 's3'
Requires-Dist: pyyaml ; extra == 's3'
Requires-Dist: asttokens ; extra == 's3'
Requires-Dist: IPython (>=7.0.0) ; extra == 's3'
Requires-Dist: jinja2 ; extra == 's3'
Requires-Dist: nbformat ; extra == 's3'
Requires-Dist: nbconvert (<7.0.0) ; extra == 's3'
Requires-Dist: requests ; extra == 's3'
Requires-Dist: fsspec ; extra == 's3'
Requires-Dist: pandas ; extra == 's3'
Requires-Dist: alembic (==1.8.0) ; extra == 's3'
Requires-Dist: cloudpickle ; extra == 's3'
Requires-Dist: typing-extensions (>=4.0.0) ; extra == 's3'
Requires-Dist: black ; extra == 's3'
Requires-Dist: isort ; extra == 's3'
Requires-Dist: boto3 ; extra == 's3'
Requires-Dist: s3fs ; extra == 's3'
Requires-Dist: botocore ; extra == 's3'
